{"file":"main-BVJJUaYD.js","mappings":";;;;;;;;;;;;;;;;;;;;;;;;;;;;;AACO,YAAA,OAAAA,eAAAC,WAAA,EAAA,OAAM,gCAA4B,MAAA,CAAA,CAAA,4MAAA;;;;;;QAW/B,SAAQ;AAAA,QACR,OAAM;AAAA,QACN,MAAK;AAAA,QACL,OAAM;AAAA,MAAA;yBAJR,CAQU,GAAAC,QAAAC,UAAA,aAAA;;;cAFF,MAAK;AAAA,cAA0B,OAAM;AAAA,YAAA;;;;cAA3CC,YAA4D,iBAAA;AAAA,gBAAtD,MAAK;AAAA,gBAA0B,OAAM;AAAA,cAAA;8BAAiB,OAE9D;AAAA,YAAA;AAAA;;;;;QAGE,SAAQ;AAAA,QACR,OAAM;AAAA,QACN,MAAK;AAAA,QACL,OAAM;AAAA,MAAA;yBAJR,CAQU,GAAAF,QAAAC,UAAA,aAAA;;;cAFF,MAAK;AAAA,cAAqC,OAAM;AAAA,YAAA;;;;cAAtDC,YAAuE,iBAAA;AAAA,gBAAjE,MAAK;AAAA,gBAAqC,OAAM;AAAA,cAAA;8BAAiB,MAEzE;AAAA,YAAA;AAAA;;;;;;QAUY,MAAK;AAAA,QAAiB,OAAM;AAAA,MAAA;;;QAS1B,IAAG;AAAA,QAAI,OAAK,CAAC,+EAA6E,EAAA,eAA0BC,KAAAA,OAAO,SAAI,IAAA,CAAA;AAAA,MAAA;yBAAzI,CAGW,GAAAH,QAAAC,UAAA,aAAA;;;cAFH,MAAK;AAAA,cAAiB,OAAM;AAAA,YAAA;;;;cAAlCC,YAA8C,iBAAA;AAAA,gBAAxC,MAAK;AAAA,gBAAiB,OAAM;AAAA,cAAA;cAClCA,YAAe,cAAT,IAAE;AAAA,YAAA;AAAA;;;;;QAGA,IAAG;AAAA,QAAwB,OAAK,CAAC,+EAA6E,EAAA,eAA0BC,KAAAA,OAAO,SAAI,wBAAA,CAAA;AAAA,MAAA;yBAA7J,CAGW,GAAAH,QAAAC,UAAA,aAAA;;;cAFH,MAAK;AAAA,cAA8B,OAAM;AAAA,YAAA;;;;cAA/CC,YAA2D,iBAAA;AAAA,gBAArD,MAAK;AAAA,gBAA8B,OAAM;AAAA,cAAA;cAC/CA,YAAkB,cAAZ,OAAK;AAAA,YAAA;AAAA;;;;;QAGH,IAAG;AAAA,QAAkB,OAAK,CAAC,+EAA6E,EAAA,eAA0BC,KAAAA,OAAO,SAAI,kBAAA,CAAA;AAAA,MAAA;yBAAvJ,CAGW,GAAAH,QAAAC,UAAA,aAAA;;;cAFH,MAAK;AAAA,cAA0B,OAAM;AAAA,YAAA;;;;cAA3CC,YAAuD,iBAAA;AAAA,gBAAjD,MAAK;AAAA,gBAA0B,OAAM;AAAA,cAAA;cAC3CA,YAAiB,cAAX,MAAI;AAAA,YAAA;AAAA;;;;;QAGF,IAAG;AAAA,QAAgB,OAAK,CAAC,+EAA6E,EAAA,eAA0BC,KAAAA,OAAO,SAAI,gBAAA,CAAA;AAAA,MAAA;yBAArJ,CAGW,GAAAH,QAAAC,UAAA,aAAA;;;cAFH,MAAK;AAAA,cAAwB,OAAM;AAAA,YAAA;;;;cAAzCC,YAAqD,iBAAA;AAAA,gBAA/C,MAAK;AAAA,gBAAwB,OAAM;AAAA,cAAA;cACzCA,YAAiB,cAAX,MAAI;AAAA,YAAA;AAAA;;;;;QAGF,IAAG;AAAA,QAAkB,OAAK,CAAC,+EAA6E,EAAA,eAA0BC,KAAAA,OAAO,SAAI,kBAAA,CAAA;AAAA,MAAA;yBAAvJ,CAGW,GAAAH,QAAAC,UAAA,aAAA;;;cAFH,MAAK;AAAA,cAAyB,OAAM;AAAA,YAAA;;;;cAA1CC,YAAsD,iBAAA;AAAA,gBAAhD,MAAK;AAAA,gBAAyB,OAAM;AAAA,cAAA;cAC1CA,YAAe,cAAT,IAAE;AAAA,YAAA;AAAA;;;;;QAGA,IAAG;AAAA,QAAgB,OAAK,CAAC,+EAA6E,EAAA,eAA0BC,KAAAA,OAAO,SAAI,gBAAA,CAAA;AAAA,MAAA;yBAArJ,CAGW,GAAAH,QAAAC,UAAA,aAAA;;;cAFH,MAAK;AAAA,cAAoC,OAAM;AAAA,YAAA;;;;cAArDC,YAAiE,iBAAA;AAAA,gBAA3D,MAAK;AAAA,gBAAoC,OAAM;AAAA,cAAA;cACrDA,YAAiB,cAAX,MAAI;AAAA,YAAA;AAAA;;;;;QAGF,IAAG;AAAA,QAAc,OAAK,CAAC,+EAA6E,EAAA,eAA0BC,KAAAA,OAAO,SAAI,cAAA,CAAA;AAAA,MAAA;yBAAnJ,CAGW,GAAAH,QAAAC,UAAA,aAAA;;;cAFH,MAAK;AAAA,cAAiB,OAAM;AAAA,YAAA;;;;cAAlCC,YAA8C,iBAAA;AAAA,gBAAxC,MAAK;AAAA,gBAAiB,OAAM;AAAA,cAAA;cAClCA,YAAsB,cAAhB,WAAS;AAAA,YAAA;AAAA;;;;;QAGP,IAAG;AAAA,QAA0B,OAAK,CAAC,+EAA6E,EAAA,eAA0BC,KAAAA,OAAO,SAAI,0BAAA,CAAA;AAAA,MAAA;yBAA/J,CAGW,GAAAH,QAAAC,UAAA,aAAA;;;cAFH,MAAK;AAAA,cAA4B,OAAM;AAAA,YAAA;;;;cAA7CC,YAAyD,iBAAA;AAAA,gBAAnD,MAAK;AAAA,gBAA4B,OAAM;AAAA,cAAA;cAC7CA,YAAiB,cAAX,MAAI;AAAA,YAAA;AAAA;;;;;;;AAaR,YAAAE,mBAAA,mBAAA,EAAA,kBAAe,yCAAqC,MAAA,OAAA,CAAA;;;;;;;;;;;;","names":["_ssrRenderAttrs","_mergeProps","_push","_parent","_createVNode","$route","_ssrRenderComponent"],"sources":["../../../../layouts/main.vue"],"sourcesContent":["<template>\r\n  <div class=\"min-h-screen flex flex-col\">\r\n    <!-- Header -->\r\n    <header class=\"navbar-gradient h-16 flex items-center px-6 shadow-sm\">\r\n      <div class=\"flex-1\"></div>\r\n      \r\n      <h1 class=\"text-white text-xl font-bold\">\r\n        <slot name=\"title\">更新會管理</slot>\r\n      </h1>\r\n      \r\n      <div class=\"flex-1 flex justify-end items-center space-x-4\">\r\n        <UButton \r\n          variant=\"ghost\" \r\n          color=\"white\" \r\n          size=\"sm\"\r\n          class=\"text-white hover:bg-green-600\"\r\n        >\r\n          <Icon name=\"heroicons:shopping-cart\" class=\"w-5 h-5 mr-2\" />\r\n          購物車\r\n        </UButton>\r\n        \r\n        <UButton \r\n          variant=\"ghost\" \r\n          color=\"white\" \r\n          size=\"sm\"\r\n          class=\"text-white hover:bg-green-600\"\r\n        >\r\n          <Icon name=\"heroicons:arrow-right-on-rectangle\" class=\"w-5 h-5 mr-2\" />\r\n          登出\r\n        </UButton>\r\n      </div>\r\n    </header>\r\n\r\n    <div class=\"flex flex-1\">\r\n      <!-- Sidebar -->\r\n      <aside class=\"w-64 bg-gray-800 min-h-full text-white\">\r\n        <div class=\"p-4\">\r\n          <div class=\"flex items-center space-x-3 mb-8\">\r\n            <div class=\"w-16 h-16 bg-gray-600 rounded-full flex items-center justify-center\">\r\n              <Icon name=\"heroicons:user\" class=\"w-8 h-8 text-white\" />\r\n            </div>\r\n            <div>\r\n              <div class=\"text-white font-medium\">許湘淳</div>\r\n              <div class=\"w-6 h-6 bg-gray-600 rounded-full mt-1\"></div>\r\n            </div>\r\n          </div>\r\n          \r\n          <nav class=\"space-y-2\">\r\n            <NuxtLink to=\"/\" class=\"flex items-center space-x-3 p-3 rounded hover:bg-gray-700 transition-colors\" :class=\"{ 'bg-blue-600': $route.path === '/' }\">\r\n              <Icon name=\"heroicons:home\" class=\"w-5 h-5\" />\r\n              <span>首頁</span>\r\n            </NuxtLink>\r\n            \r\n            <NuxtLink to=\"/tables/urban-renewal\" class=\"flex items-center space-x-3 p-3 rounded hover:bg-gray-700 transition-colors\" :class=\"{ 'bg-blue-600': $route.path === '/tables/urban-renewal' }\">\r\n              <Icon name=\"heroicons:building-office-2\" class=\"w-5 h-5\" />\r\n              <span>更新會管理</span>\r\n            </NuxtLink>\r\n            \r\n            <NuxtLink to=\"/tables/meeting\" class=\"flex items-center space-x-3 p-3 rounded hover:bg-gray-700 transition-colors\" :class=\"{ 'bg-blue-600': $route.path === '/tables/meeting' }\">\r\n              <Icon name=\"heroicons:document-text\" class=\"w-5 h-5\" />\r\n              <span>會議管理</span>\r\n            </NuxtLink>\r\n            \r\n            <NuxtLink to=\"/tables/issue\" class=\"flex items-center space-x-3 p-3 rounded hover:bg-gray-700 transition-colors\" :class=\"{ 'bg-blue-600': $route.path === '/tables/issue' }\">\r\n              <Icon name=\"heroicons:check-badge\" class=\"w-5 h-5\" />\r\n              <span>投票管理</span>\r\n            </NuxtLink>\r\n            \r\n            <NuxtLink to=\"/pages/shopping\" class=\"flex items-center space-x-3 p-3 rounded hover:bg-gray-700 transition-colors\" :class=\"{ 'bg-blue-600': $route.path === '/pages/shopping' }\">\r\n              <Icon name=\"heroicons:shopping-bag\" class=\"w-5 h-5\" />\r\n              <span>商城</span>\r\n            </NuxtLink>\r\n            \r\n            <NuxtLink to=\"/tables/order\" class=\"flex items-center space-x-3 p-3 rounded hover:bg-gray-700 transition-colors\" :class=\"{ 'bg-blue-600': $route.path === '/tables/order' }\">\r\n              <Icon name=\"heroicons:clipboard-document-list\" class=\"w-5 h-5\" />\r\n              <span>購買紀錄</span>\r\n            </NuxtLink>\r\n            \r\n            <NuxtLink to=\"/pages/user\" class=\"flex items-center space-x-3 p-3 rounded hover:bg-gray-700 transition-colors\" :class=\"{ 'bg-blue-600': $route.path === '/pages/user' }\">\r\n              <Icon name=\"heroicons:user\" class=\"w-5 h-5\" />\r\n              <span>使用者基本資料變更</span>\r\n            </NuxtLink>\r\n            \r\n            <NuxtLink to=\"/tables/company-profile\" class=\"flex items-center space-x-3 p-3 rounded hover:bg-gray-700 transition-colors\" :class=\"{ 'bg-blue-600': $route.path === '/tables/company-profile' }\">\r\n              <Icon name=\"heroicons:building-office\" class=\"w-5 h-5\" />\r\n              <span>企業管理</span>\r\n            </NuxtLink>\r\n          </nav>\r\n        </div>\r\n      </aside>\r\n\r\n      <!-- Main Content -->\r\n      <main class=\"flex-1 bg-gray-50 flex flex-col\">\r\n        <div class=\"flex-1 p-6\">\r\n          <div class=\"bg-white rounded-lg shadow-lg h-full p-6\">\r\n            <slot />\r\n          </div>\r\n        </div>\r\n        <Footer copyright-text=\"© 2020, made with ❤️ by Thread Tech\" />\r\n      </main>\r\n    </div>\r\n  </div>\r\n</template>\r\n\r\n<script setup>\r\n// Main layout for authenticated pages\r\n</script>\r\n\r\n<style scoped>\r\n.navbar-gradient {\r\n  background: linear-gradient(to right, #2FA633, #72BB29);\r\n}\r\n</style>"],"version":3}